{
	"configurations" : 
	[
		{
			"directories" : 
			[
				{
					"build" : ".",
					"hasInstallRule" : true,
					"jsonFile" : "directory-.-1cd434d8c182ca9ca7e8.json",
					"minimumCMakeVersion" : 
					{
						"string" : "3.12"
					},
					"projectIndex" : 0,
					"source" : ".",
					"targetIndexes" : 
					[
						0,
						1,
						2,
						3
					]
				}
			],
			"name" : "",
			"projects" : 
			[
				{
					"directoryIndexes" : 
					[
						0
					],
					"name" : "generic_motor_driver",
					"targetIndexes" : 
					[
						0,
						1,
						2,
						3
					]
				}
			],
			"targets" : 
			[
				{
					"directoryIndex" : 0,
					"id" : "generic_motor_driver::@6890427a1f51a3e7e1df",
					"jsonFile" : "target-generic_motor_driver-9b7121f09bba1139b1cf.json",
					"name" : "generic_motor_driver",
					"projectIndex" : 0
				},
				{
					"directoryIndex" : 0,
					"id" : "generic_motor_driver_uninstall::@6890427a1f51a3e7e1df",
					"jsonFile" : "target-generic_motor_driver_uninstall-b4c8c9c59de3cc791734.json",
					"name" : "generic_motor_driver_uninstall",
					"projectIndex" : 0
				},
				{
					"directoryIndex" : 0,
					"id" : "relay_controller::@6890427a1f51a3e7e1df",
					"jsonFile" : "target-relay_controller-18e7b605623b3f9467bc.json",
					"name" : "relay_controller",
					"projectIndex" : 0
				},
				{
					"directoryIndex" : 0,
					"id" : "uninstall::@6890427a1f51a3e7e1df",
					"jsonFile" : "target-uninstall-109285564e1a42364006.json",
					"name" : "uninstall",
					"projectIndex" : 0
				}
			]
		}
	],
	"kind" : "codemodel",
	"paths" : 
	{
		"build" : "/home/user/test_ws/build/generic_motor_driver",
		"source" : "/home/user/test_ws/src/create_robot/create_driver"
	},
	"version" : 
	{
		"major" : 2,
		"minor" : 3
	}
}
